pyopenls9.abi3.so
pyopenls9-1.1.0.dist-info/METADATA
pyopenls9-1.1.0.dist-info/WHEEL
pyopenls9-1.1.0.dist-info/top_level.txt
pyopenls9-1.1.0.dist-info/RECORD
