Metadata-Version: 2.1
Name: pyopenls9
Version: 1.1.0
Summary: A library to control the Yamaha LS9
Home-page: http://github.com/nixCodeX/open-ls9-control
Author: Jonathan Tanner
License: UNKNOWN
Platform: UNKNOWN
